mobuild/__init__.py
mobuild/__main__.py
mobuild/py.typed
mobuild/static/cookiecutter/cookiecutter.json
mobuild/static/cookiecutter/{{cookiecutter.project_name}}/Makefile
mobuild/static/cookiecutter/{{cookiecutter.project_name}}/README.md
mobuild/static/cookiecutter/{{cookiecutter.project_name}}/pyproject.toml
mobuild/static/cookiecutter/{{cookiecutter.project_name}}/nbs/__init__.py
mobuild/static/cookiecutter/{{cookiecutter.project_name}}/tests/test_basic.py
mobuild-0.1.1.dist-info/METADATA
mobuild-0.1.1.dist-info/WHEEL
mobuild-0.1.1.dist-info/entry_points.txt
mobuild-0.1.1.dist-info/licenses/LICENSE
mobuild-0.1.1.dist-info/RECORD
