Metadata-Version: 2.4
Name: mobuild
Version: 0.1.1
Summary: Add your description here
Author-email: koaning <vincentwarmerdam@gmail.com>
License-File: LICENSE
Requires-Python: >=3.12
Requires-Dist: cookiecutter
Requires-Dist: marimo
Requires-Dist: typer
